dj_maintenance/__init__.py
dj_maintenance/admin.py
dj_maintenance/apps.py
dj_maintenance/models.py
dj_maintenance/tests.py
dj_maintenance/urls.py
dj_maintenance/views.py
dj_maintenance/migrations/__init__.py
dj_maintenance/static/dj-maintenance/images/maintenance.gif
dj_maintenance/templates/dj_maintenance/index.html
dj_maintenance-0.2.6.dist-info/LICENSE
dj_maintenance-0.2.6.dist-info/METADATA
dj_maintenance-0.2.6.dist-info/WHEEL
dj_maintenance-0.2.6.dist-info/top_level.txt
dj_maintenance-0.2.6.dist-info/RECORD
