Metadata-Version: 2.1
Name: dj-maintenance
Version: 0.2.6
Summary: A django app to conduct sheduled maintenance.
Home-page: https://djmaintenance.ayumefrancis.com/
Author: Ayume Francis
Author-email: admin@ayumefrancis.com
License: BSD-3-Clause
Project-URL: Homepage, https://djmaintenance.ayumefrancis.com
Project-URL: Source Code, https://github.com/ayudmin/dj_maintenance
Classifier: Environment :: Web Environment
Classifier: Framework :: Django
Classifier: Framework :: Django :: 4.2
Classifier: Intended Audience :: Developers
Classifier: License :: OSI Approved :: BSD License
Classifier: Operating System :: OS Independent
Classifier: Programming Language :: Python
Classifier: Programming Language :: Python :: 3
Classifier: Programming Language :: Python :: 3 :: Only
Classifier: Programming Language :: Python :: 3.8
Classifier: Programming Language :: Python :: 3.9
Classifier: Topic :: Internet :: WWW/HTTP
Classifier: Topic :: Internet :: WWW/HTTP :: Dynamic Content
Requires-Python: >=3.8
License-File: LICENSE
Requires-Dist: Django (>=4.2)
